{
  "tweet": {
    "edit_info": {
      "initial": {
        "editTweetIds": [
          "992424158897278983"
        ],
        "editableUntil": "2018-05-04T16:22:12.487Z",
        "editsRemaining": "5",
        "isEditEligible": true
      }
    },
    "retweeted": false,
    "source": "<a href=\"http://twitter.com\" rel=\"nofollow\">Twitter Web Client</a>",
    "entities": {
      "hashtags": [],
      "symbols": [],
      "user_mentions": [
        {
          "name": "Aureylian",
          "screen_name": "aureylian",
          "indices": [
            "3",
            "13"
          ],
          "id_str": "206263351",
          "id": "206263351"
        },
        {
          "name": "ＭΛＮ",
          "screen_name": "MANvsGAME",
          "indices": [
            "15",
            "25"
          ],
          "id_str": "43366650",
          "id": "43366650"
        },
        {
          "name": "Cowsep",
          "screen_name": "Cowsep",
          "indices": [
            "26",
            "33"
          ],
          "id_str": "2431356582",
          "id": "2431356582"
        },
        {
          "name": "Twitch",
          "screen_name": "Twitch",
          "indices": [
            "34",
            "41"
          ],
          "id_str": "309366491",
          "id": "309366491"
        }
      ],
      "urls": [
        {
          "url": "https://t.co/DgBjfZJCUd",
          "expanded_url": "https://help.twitch.tv/customer/en/portal/articles/2935005-low-latency-video-beta",
          "display_url": "help.twitch.tv/customer/en/po…",
          "indices": [
            "93",
            "116"
          ]
        }
      ]
    },
    "display_text_range": [
      "0",
      "139"
    ],
    "favorite_count": "0",
    "id_str": "992424158897278983",
    "truncated": false,
    "retweet_count": "0",
    "id": "992424158897278983",
    "possibly_sensitive": false,
    "created_at": "Fri May 04 15:22:12 +0000 2018",
    "favorited": false,
    "full_text": "RT @aureylian: @MANvsGAME @Cowsep @Twitch Here's more information overall about Low Latency: https://t.co/DgBjfZJCUd\n\nbut you can check to…",
    "lang": "en"
  }
}