{
  "tweet": {
    "edit_info": {
      "initial": {
        "editTweetIds": [
          "1219707056191614976"
        ],
        "editableUntil": "2020-01-21T20:43:17.914Z",
        "editsRemaining": "5",
        "isEditEligible": true
      }
    },
    "retweeted": false,
    "source": "<a href=\"http://twitter.com/download/iphone\" rel=\"nofollow\">Twitter for iPhone</a>",
    "entities": {
      "hashtags": [],
      "symbols": [],
      "user_mentions": [
        {
          "name": "Brandy Jensen",
          "screen_name": "BrandyLJensen",
          "indices": [
            "3",
            "17"
          ],
          "id_str": "3099901028",
          "id": "3099901028"
        }
      ],
      "urls": []
    },
    "display_text_range": [
      "0",
      "139"
    ],
    "favorite_count": "0",
    "id_str": "1219707056191614976",
    "truncated": false,
    "retweet_count": "0",
    "id": "1219707056191614976",
    "created_at": "Tue Jan 21 19:43:17 +0000 2020",
    "favorited": false,
    "full_text": "RT @BrandyLJensen: pitching an HGTV show called Healthy Boundaries where I firmly refuse to renovate historic homes into open-plan layouts…",
    "lang": "en"
  }
}