{
  "tweet": {
    "edit_info": {
      "initial": {
        "editTweetIds": [
          "941153905215451137"
        ],
        "editableUntil": "2017-12-14T04:52:31.454Z",
        "editsRemaining": "5",
        "isEditEligible": true
      }
    },
    "retweeted": false,
    "source": "<a href=\"http://twitter.com/download/iphone\" rel=\"nofollow\">Twitter for iPhone</a>",
    "entities": {
      "hashtags": [],
      "symbols": [],
      "user_mentions": [
        {
          "name": "PIPe",
          "screen_name": "PIPeJTV",
          "indices": [
            "0",
            "8"
          ],
          "id_str": "297578568",
          "id": "297578568"
        }
      ],
      "urls": []
    },
    "display_text_range": [
      "0",
      "13"
    ],
    "favorite_count": "1",
    "in_reply_to_status_id_str": "941153313554300928",
    "id_str": "941153905215451137",
    "in_reply_to_user_id": "297578568",
    "truncated": false,
    "retweet_count": "0",
    "id": "941153905215451137",
    "in_reply_to_status_id": "941153313554300928",
    "created_at": "Thu Dec 14 03:52:31 +0000 2017",
    "favorited": false,
    "full_text": "@PIPeJTV siCk",
    "lang": "en",
    "in_reply_to_screen_name": "PIPeJTV",
    "in_reply_to_user_id_str": "297578568"
  }
}