{
  "tweet": {
    "edit_info": {
      "initial": {
        "editTweetIds": [
          "1018300863700459520"
        ],
        "editableUntil": "2018-07-15T02:06:59.678Z",
        "editsRemaining": "5",
        "isEditEligible": true
      }
    },
    "retweeted": false,
    "source": "<a href=\"http://twitter.com\" rel=\"nofollow\">Twitter Web Client</a>",
    "entities": {
      "user_mentions": [
        {
          "name": "Downtown Dave",
          "screen_name": "BigHatPosse",
          "indices": [
            "3",
            "15"
          ],
          "id_str": "750407125428383744",
          "id": "750407125428383744"
        }
      ],
      "urls": [],
      "symbols": [],
      "media": [
        {
          "expanded_url": "https://twitter.com/BigHatPosse/status/1017774640477954048/video/1",
          "source_status_id": "1017774640477954048",
          "indices": [
            "112",
            "135"
          ],
          "url": "https://t.co/JtYiSGYxwJ",
          "media_url": "http://pbs.twimg.com/ext_tw_video_thumb/1017774606290046977/pu/img/5D-1ndEkXsWYK_3q.jpg",
          "id_str": "1017774606290046977",
          "source_user_id": "750407125428383744",
          "id": "1017774606290046977",
          "media_url_https": "https://pbs.twimg.com/ext_tw_video_thumb/1017774606290046977/pu/img/5D-1ndEkXsWYK_3q.jpg",
          "source_user_id_str": "750407125428383744",
          "sizes": {
            "medium": {
              "w": "675",
              "h": "1200",
              "resize": "fit"
            },
            "large": {
              "w": "720",
              "h": "1280",
              "resize": "fit"
            },
            "thumb": {
              "w": "150",
              "h": "150",
              "resize": "crop"
            },
            "small": {
              "w": "383",
              "h": "680",
              "resize": "fit"
            }
          },
          "type": "photo",
          "source_status_id_str": "1017774640477954048",
          "display_url": "pic.twitter.com/JtYiSGYxwJ"
        }
      ],
      "hashtags": [
        {
          "text": "Bats",
          "indices": [
            "106",
            "111"
          ]
        }
      ]
    },
    "display_text_range": [
      "0",
      "135"
    ],
    "favorite_count": "0",
    "id_str": "1018300863700459520",
    "truncated": false,
    "retweet_count": "0",
    "id": "1018300863700459520",
    "possibly_sensitive": false,
    "created_at": "Sun Jul 15 01:06:59 +0000 2018",
    "favorited": false,
    "full_text": "RT @BigHatPosse: Every year the bats make a visit to our office.  It must be that time of the year again. #Bats https://t.co/JtYiSGYxwJ",
    "lang": "en",
    "extended_entities": {
      "media": [
        {
          "expanded_url": "https://twitter.com/BigHatPosse/status/1017774640477954048/video/1",
          "source_status_id": "1017774640477954048",
          "indices": [
            "112",
            "135"
          ],
          "url": "https://t.co/JtYiSGYxwJ",
          "media_url": "http://pbs.twimg.com/ext_tw_video_thumb/1017774606290046977/pu/img/5D-1ndEkXsWYK_3q.jpg",
          "id_str": "1017774606290046977",
          "video_info": {
            "aspect_ratio": [
              "9",
              "16"
            ],
            "duration_millis": "10967",
            "variants": [
              {
                "bitrate": "256000",
                "content_type": "video/mp4",
                "url": "https://video.twimg.com/ext_tw_video/1017774606290046977/pu/vid/180x320/Ic3MFXy8qnkF5scI.mp4?tag=3"
              },
              {
                "content_type": "application/x-mpegURL",
                "url": "https://video.twimg.com/ext_tw_video/1017774606290046977/pu/pl/fbUtnyDaizKuoqHt.m3u8?tag=3"
              },
              {
                "bitrate": "832000",
                "content_type": "video/mp4",
                "url": "https://video.twimg.com/ext_tw_video/1017774606290046977/pu/vid/360x640/mwEBwoNPjI2r8Gju.mp4?tag=3"
              },
              {
                "bitrate": "2176000",
                "content_type": "video/mp4",
                "url": "https://video.twimg.com/ext_tw_video/1017774606290046977/pu/vid/720x1280/4j04SMnM2KUeymdK.mp4?tag=3"
              }
            ]
          },
          "source_user_id": "750407125428383744",
          "additional_media_info": {
            "monetizable": false
          },
          "id": "1017774606290046977",
          "media_url_https": "https://pbs.twimg.com/ext_tw_video_thumb/1017774606290046977/pu/img/5D-1ndEkXsWYK_3q.jpg",
          "source_user_id_str": "750407125428383744",
          "sizes": {
            "medium": {
              "w": "675",
              "h": "1200",
              "resize": "fit"
            },
            "large": {
              "w": "720",
              "h": "1280",
              "resize": "fit"
            },
            "thumb": {
              "w": "150",
              "h": "150",
              "resize": "crop"
            },
            "small": {
              "w": "383",
              "h": "680",
              "resize": "fit"
            }
          },
          "type": "video",
          "source_status_id_str": "1017774640477954048",
          "display_url": "pic.twitter.com/JtYiSGYxwJ"
        }
      ]
    }
  }
}