{
  "tweet": {
    "edit_info": {
      "initial": {
        "editTweetIds": [
          "1206317734155489280"
        ],
        "editableUntil": "2019-12-15T21:58:54.779Z",
        "editsRemaining": "5",
        "isEditEligible": true
      }
    },
    "retweeted": false,
    "source": "<a href=\"https://mobile.twitter.com\" rel=\"nofollow\">Twitter Web App</a>",
    "entities": {
      "hashtags": [],
      "symbols": [],
      "user_mentions": [],
      "urls": []
    },
    "display_text_range": [
      "0",
      "125"
    ],
    "favorite_count": "9",
    "id_str": "1206317734155489280",
    "truncated": false,
    "retweet_count": "1",
    "id": "1206317734155489280",
    "created_at": "Sun Dec 15 20:58:54 +0000 2019",
    "favorited": false,
    "full_text": "do not use your applications notification tray to send me a notification that your application has notifications!!! do not!!!",
    "lang": "en"
  }
}