{
  "tweet": {
    "edit_info": {
      "initial": {
        "editTweetIds": [
          "1354966039466029060"
        ],
        "editableUntil": "2021-01-29T02:34:12.517Z",
        "editsRemaining": "5",
        "isEditEligible": true
      }
    },
    "retweeted": false,
    "source": "<a href=\"https://mobile.twitter.com\" rel=\"nofollow\">Twitter Web App</a>",
    "entities": {
      "user_mentions": [
        {
          "name": "",
          "screen_name": "Kx9f5tsmAkemi",
          "indices": [
            "3",
            "17"
          ],
          "id_str": "-1",
          "id": "-1"
        }
      ],
      "urls": [],
      "symbols": [],
      "media": [
        {
          "expanded_url": "https://twitter.com/Kx9f5tsmAkemi/status/1354577187718848518/photo/1",
          "source_status_id": "1354577187718848518",
          "indices": [
            "32",
            "55"
          ],
          "url": "https://t.co/D4wD1dlSdP",
          "media_url": "http://pbs.twimg.com/media/Esxsxb4UYAIIgmG.jpg",
          "id_str": "1354577184485040130",
          "source_user_id": "917425294373380097",
          "id": "1354577184485040130",
          "media_url_https": "https://pbs.twimg.com/media/Esxsxb4UYAIIgmG.jpg",
          "source_user_id_str": "917425294373380097",
          "sizes": {
            "thumb": {
              "w": "150",
              "h": "150",
              "resize": "crop"
            },
            "medium": {
              "w": "1200",
              "h": "899",
              "resize": "fit"
            },
            "small": {
              "w": "680",
              "h": "510",
              "resize": "fit"
            },
            "large": {
              "w": "2048",
              "h": "1535",
              "resize": "fit"
            }
          },
          "type": "photo",
          "source_status_id_str": "1354577187718848518",
          "display_url": "pic.twitter.com/D4wD1dlSdP"
        }
      ],
      "hashtags": []
    },
    "display_text_range": [
      "0",
      "55"
    ],
    "favorite_count": "0",
    "id_str": "1354966039466029060",
    "truncated": false,
    "retweet_count": "0",
    "id": "1354966039466029060",
    "possibly_sensitive": false,
    "created_at": "Fri Jan 29 01:34:12 +0000 2021",
    "favorited": false,
    "full_text": "RT @Kx9f5tsmAkemi: 昨夜鳥会議がありました。 https://t.co/D4wD1dlSdP",
    "lang": "ja",
    "extended_entities": {
      "media": [
        {
          "expanded_url": "https://twitter.com/Kx9f5tsmAkemi/status/1354577187718848518/photo/1",
          "source_status_id": "1354577187718848518",
          "indices": [
            "32",
            "55"
          ],
          "url": "https://t.co/D4wD1dlSdP",
          "media_url": "http://pbs.twimg.com/media/Esxsxb4UYAIIgmG.jpg",
          "id_str": "1354577184485040130",
          "source_user_id": "917425294373380097",
          "id": "1354577184485040130",
          "media_url_https": "https://pbs.twimg.com/media/Esxsxb4UYAIIgmG.jpg",
          "source_user_id_str": "917425294373380097",
          "sizes": {
            "thumb": {
              "w": "150",
              "h": "150",
              "resize": "crop"
            },
            "medium": {
              "w": "1200",
              "h": "899",
              "resize": "fit"
            },
            "small": {
              "w": "680",
              "h": "510",
              "resize": "fit"
            },
            "large": {
              "w": "2048",
              "h": "1535",
              "resize": "fit"
            }
          },
          "type": "photo",
          "source_status_id_str": "1354577187718848518",
          "display_url": "pic.twitter.com/D4wD1dlSdP"
        }
      ]
    }
  }
}