{
  "tweet": {
    "edit_info": {
      "initial": {
        "editTweetIds": [
          "1096755424873852928"
        ],
        "editableUntil": "2019-02-16T13:57:24.677Z",
        "editsRemaining": "5",
        "isEditEligible": true
      }
    },
    "retweeted": false,
    "source": "<a href=\"http://twitter.com/download/iphone\" rel=\"nofollow\">Twitter for iPhone</a>",
    "entities": {
      "hashtags": [],
      "symbols": [],
      "user_mentions": [
        {
          "name": "Brute Logic",
          "screen_name": "BRuteLogic",
          "indices": [
            "0",
            "11"
          ],
          "id_str": "84484829",
          "id": "84484829"
        },
        {
          "name": "Hisxo",
          "screen_name": "adrien_jeanneau",
          "indices": [
            "12",
            "28"
          ],
          "id_str": "91375403",
          "id": "91375403"
        }
      ],
      "urls": []
    },
    "display_text_range": [
      "0",
      "112"
    ],
    "favorite_count": "1",
    "in_reply_to_status_id_str": "1096752641315667969",
    "id_str": "1096755424873852928",
    "in_reply_to_user_id": "84484829",
    "truncated": false,
    "retweet_count": "0",
    "id": "1096755424873852928",
    "in_reply_to_status_id": "1096752641315667969",
    "created_at": "Sat Feb 16 12:57:24 +0000 2019",
    "favorited": false,
    "full_text": "@brutelogic @adrien_jeanneau isn’t ‘remote script import’ like tbe definition of ‘cross-site scripting’ already?",
    "lang": "en",
    "in_reply_to_screen_name": "BRuteLogic",
    "in_reply_to_user_id_str": "84484829"
  }
}