{
  "tweet": {
    "edit_info": {
      "initial": {
        "editTweetIds": [
          "830999905250508800"
        ],
        "editableUntil": "2017-02-13T05:39:51.300Z",
        "editsRemaining": "5",
        "isEditEligible": true
      }
    },
    "retweeted": false,
    "source": "<a href=\"http://twitter.com\" rel=\"nofollow\">Twitter Web Client</a>",
    "entities": {
      "hashtags": [],
      "symbols": [],
      "user_mentions": [],
      "urls": []
    },
    "display_text_range": [
      "0",
      "137"
    ],
    "favorite_count": "0",
    "id_str": "830999905250508800",
    "truncated": false,
    "retweet_count": "0",
    "id": "830999905250508800",
    "created_at": "Mon Feb 13 04:39:51 +0000 2017",
    "favorited": false,
    "full_text": "resident evil 7 is pretty disgusting for people, but for detritivores like maggots and worms it's basically a 12 hour cut of Chef's Table",
    "lang": "en"
  }
}