{
  "tweet": {
    "edit_info": {
      "initial": {
        "editTweetIds": [
          "1141973300828155904"
        ],
        "editableUntil": "2019-06-21T08:37:06.412Z",
        "editsRemaining": "5",
        "isEditEligible": true
      }
    },
    "retweeted": false,
    "source": "<a href=\"http://twitter.com/download/iphone\" rel=\"nofollow\">Twitter for iPhone</a>",
    "entities": {
      "hashtags": [],
      "symbols": [],
      "user_mentions": [
        {
          "name": "Cody Conners",
          "screen_name": "evoli",
          "indices": [
            "0",
            "6"
          ],
          "id_str": "208645319",
          "id": "208645319"
        }
      ],
      "urls": []
    },
    "display_text_range": [
      "0",
      "12"
    ],
    "favorite_count": "0",
    "in_reply_to_status_id_str": "1141809062339731456",
    "id_str": "1141973300828155904",
    "in_reply_to_user_id": "208645319",
    "truncated": false,
    "retweet_count": "0",
    "id": "1141973300828155904",
    "in_reply_to_status_id": "1141809062339731456",
    "created_at": "Fri Jun 21 07:37:06 +0000 2019",
    "favorited": false,
    "full_text": "@evoli water",
    "lang": "en",
    "in_reply_to_screen_name": "evoli",
    "in_reply_to_user_id_str": "208645319"
  }
}