{
  "tweet": {
    "edit_info": {
      "initial": {
        "editTweetIds": [
          "1357442008722403331"
        ],
        "editableUntil": "2021-02-04T22:32:49.589Z",
        "editsRemaining": "5",
        "isEditEligible": true
      }
    },
    "retweeted": false,
    "source": "<a href=\"https://mobile.twitter.com\" rel=\"nofollow\">Twitter Web App</a>",
    "entities": {
      "hashtags": [],
      "symbols": [],
      "user_mentions": [
        {
          "name": "summertime scent roll",
          "screen_name": "ruderubik",
          "indices": [
            "0",
            "10"
          ],
          "id_str": "1429691460597665793",
          "id": "1429691460597665793"
        },
        {
          "name": "niki c",
          "screen_name": "inventednight",
          "indices": [
            "11",
            "25"
          ],
          "id_str": "735701512127533057",
          "id": "735701512127533057"
        }
      ],
      "urls": []
    },
    "display_text_range": [
      "0",
      "193"
    ],
    "favorite_count": "0",
    "in_reply_to_status_id_str": "1357441246046785536",
    "id_str": "1357442008722403331",
    "in_reply_to_user_id": "915162007602585601",
    "truncated": false,
    "retweet_count": "0",
    "id": "1357442008722403331",
    "in_reply_to_status_id": "1357441246046785536",
    "created_at": "Thu Feb 04 21:32:49 +0000 2021",
    "favorited": false,
    "full_text": "@ruderubik @inventednight i really think that it's key that a lot of things would be more accessible to people with adhd if they were taught, and / or expected to be executed in a different way",
    "lang": "en",
    "in_reply_to_user_id_str": "915162007602585601"
  }
}