{
  "tweet": {
    "edit_info": {
      "initial": {
        "editTweetIds": [
          "1195576027277398016"
        ],
        "editableUntil": "2019-11-16T06:35:12.288Z",
        "editsRemaining": "5",
        "isEditEligible": true
      }
    },
    "retweeted": false,
    "source": "<a href=\"http://twitter.com/download/iphone\" rel=\"nofollow\">Twitter for iPhone</a>",
    "entities": {
      "user_mentions": [
        {
          "name": "Matthew Ferrari",
          "screen_name": "MatthewFerrari",
          "indices": [
            "3",
            "18"
          ],
          "id_str": "348698075",
          "id": "348698075"
        }
      ],
      "urls": [],
      "symbols": [],
      "media": [
        {
          "expanded_url": "https://twitter.com/MatthewFerrari/status/1195492542567141378/photo/1",
          "source_status_id": "1195492542567141378",
          "indices": [
            "20",
            "43"
          ],
          "url": "https://t.co/hVqHJJkk7x",
          "media_url": "http://pbs.twimg.com/media/EJc-IMzWkAEqsa_.jpg",
          "id_str": "1195492536686645249",
          "source_user_id": "348698075",
          "id": "1195492536686645249",
          "media_url_https": "https://pbs.twimg.com/media/EJc-IMzWkAEqsa_.jpg",
          "source_user_id_str": "348698075",
          "sizes": {
            "medium": {
              "w": "1200",
              "h": "999",
              "resize": "fit"
            },
            "large": {
              "w": "1218",
              "h": "1014",
              "resize": "fit"
            },
            "thumb": {
              "w": "150",
              "h": "150",
              "resize": "crop"
            },
            "small": {
              "w": "680",
              "h": "566",
              "resize": "fit"
            }
          },
          "type": "photo",
          "source_status_id_str": "1195492542567141378",
          "display_url": "pic.twitter.com/hVqHJJkk7x"
        }
      ],
      "hashtags": []
    },
    "display_text_range": [
      "0",
      "43"
    ],
    "favorite_count": "0",
    "id_str": "1195576027277398016",
    "truncated": false,
    "retweet_count": "0",
    "id": "1195576027277398016",
    "possibly_sensitive": false,
    "created_at": "Sat Nov 16 05:35:12 +0000 2019",
    "favorited": false,
    "full_text": "RT @MatthewFerrari: https://t.co/hVqHJJkk7x",
    "lang": "zxx",
    "extended_entities": {
      "media": [
        {
          "expanded_url": "https://twitter.com/MatthewFerrari/status/1195492542567141378/photo/1",
          "source_status_id": "1195492542567141378",
          "indices": [
            "20",
            "43"
          ],
          "url": "https://t.co/hVqHJJkk7x",
          "media_url": "http://pbs.twimg.com/media/EJc-IMzWkAEqsa_.jpg",
          "id_str": "1195492536686645249",
          "source_user_id": "348698075",
          "id": "1195492536686645249",
          "media_url_https": "https://pbs.twimg.com/media/EJc-IMzWkAEqsa_.jpg",
          "source_user_id_str": "348698075",
          "sizes": {
            "medium": {
              "w": "1200",
              "h": "999",
              "resize": "fit"
            },
            "large": {
              "w": "1218",
              "h": "1014",
              "resize": "fit"
            },
            "thumb": {
              "w": "150",
              "h": "150",
              "resize": "crop"
            },
            "small": {
              "w": "680",
              "h": "566",
              "resize": "fit"
            }
          },
          "type": "photo",
          "source_status_id_str": "1195492542567141378",
          "display_url": "pic.twitter.com/hVqHJJkk7x"
        },
        {
          "expanded_url": "https://twitter.com/MatthewFerrari/status/1195492542567141378/photo/1",
          "source_status_id": "1195492542567141378",
          "indices": [
            "20",
            "43"
          ],
          "url": "https://t.co/hVqHJJkk7x",
          "media_url": "http://pbs.twimg.com/media/EJc-IMzWkAAuNs9.jpg",
          "id_str": "1195492536686645248",
          "source_user_id": "348698075",
          "id": "1195492536686645248",
          "media_url_https": "https://pbs.twimg.com/media/EJc-IMzWkAAuNs9.jpg",
          "source_user_id_str": "348698075",
          "sizes": {
            "small": {
              "w": "589",
              "h": "320",
              "resize": "fit"
            },
            "large": {
              "w": "589",
              "h": "320",
              "resize": "fit"
            },
            "thumb": {
              "w": "150",
              "h": "150",
              "resize": "crop"
            },
            "medium": {
              "w": "589",
              "h": "320",
              "resize": "fit"
            }
          },
          "type": "photo",
          "source_status_id_str": "1195492542567141378",
          "display_url": "pic.twitter.com/hVqHJJkk7x"
        }
      ]
    }
  }
}