{
  "tweet": {
    "edit_info": {
      "initial": {
        "editTweetIds": [
          "1504521837115437090"
        ],
        "editableUntil": "2022-03-17T19:15:33.289Z",
        "editsRemaining": "5",
        "isEditEligible": true
      }
    },
    "retweeted": false,
    "source": "<a href=\"http://twitter.com/download/iphone\" rel=\"nofollow\">Twitter for iPhone</a>",
    "entities": {
      "user_mentions": [
        {
          "name": "PIPe",
          "screen_name": "PIPeJTV",
          "indices": [
            "1",
            "9"
          ],
          "id_str": "297578568",
          "id": "297578568"
        }
      ],
      "urls": [],
      "symbols": [],
      "media": [
        {
          "expanded_url": "https://twitter.com/zemnmez/status/1504521837115437090/video/1",
          "indices": [
            "39",
            "62"
          ],
          "url": "https://t.co/kvn1W0ZODD",
          "media_url": "http://pbs.twimg.com/ext_tw_video_thumb/1504521811479851019/pu/img/uTUrNiidnp_pZD5y.jpg",
          "id_str": "1504521811479851019",
          "id": "1504521811479851019",
          "media_url_https": "https://pbs.twimg.com/ext_tw_video_thumb/1504521811479851019/pu/img/uTUrNiidnp_pZD5y.jpg",
          "sizes": {
            "large": {
              "w": "640",
              "h": "360",
              "resize": "fit"
            },
            "small": {
              "w": "640",
              "h": "360",
              "resize": "fit"
            },
            "thumb": {
              "w": "150",
              "h": "150",
              "resize": "crop"
            },
            "medium": {
              "w": "640",
              "h": "360",
              "resize": "fit"
            }
          },
          "type": "photo",
          "display_url": "pic.twitter.com/kvn1W0ZODD"
        }
      ],
      "hashtags": []
    },
    "display_text_range": [
      "0",
      "62"
    ],
    "favorite_count": "19",
    "id_str": "1504521837115437090",
    "truncated": false,
    "retweet_count": "2",
    "id": "1504521837115437090",
    "possibly_sensitive": false,
    "created_at": "Thu Mar 17 18:15:33 +0000 2022",
    "favorited": false,
    "full_text": ".@PIPeJTV sent me this ancient classic https://t.co/kvn1W0ZODD",
    "lang": "en",
    "extended_entities": {
      "media": [
        {
          "expanded_url": "https://twitter.com/zemnmez/status/1504521837115437090/video/1",
          "indices": [
            "39",
            "62"
          ],
          "url": "https://t.co/kvn1W0ZODD",
          "media_url": "http://pbs.twimg.com/ext_tw_video_thumb/1504521811479851019/pu/img/uTUrNiidnp_pZD5y.jpg",
          "id_str": "1504521811479851019",
          "video_info": {
            "aspect_ratio": [
              "16",
              "9"
            ],
            "duration_millis": "22446",
            "variants": [
              {
                "content_type": "application/x-mpegURL",
                "url": "https://video.twimg.com/ext_tw_video/1504521811479851019/pu/pl/mGiKYDt1Pl2jtq26.m3u8?tag=12"
              },
              {
                "bitrate": "832000",
                "content_type": "video/mp4",
                "url": "https://video.twimg.com/ext_tw_video/1504521811479851019/pu/vid/640x360/ACSaw5-_b78CMgL3.mp4?tag=12"
              },
              {
                "bitrate": "256000",
                "content_type": "video/mp4",
                "url": "https://video.twimg.com/ext_tw_video/1504521811479851019/pu/vid/480x270/CuGE_GaLzaS7Tmdm.mp4?tag=12"
              }
            ]
          },
          "additional_media_info": {
            "monetizable": false
          },
          "id": "1504521811479851019",
          "media_url_https": "https://pbs.twimg.com/ext_tw_video_thumb/1504521811479851019/pu/img/uTUrNiidnp_pZD5y.jpg",
          "sizes": {
            "large": {
              "w": "640",
              "h": "360",
              "resize": "fit"
            },
            "small": {
              "w": "640",
              "h": "360",
              "resize": "fit"
            },
            "thumb": {
              "w": "150",
              "h": "150",
              "resize": "crop"
            },
            "medium": {
              "w": "640",
              "h": "360",
              "resize": "fit"
            }
          },
          "type": "video",
          "display_url": "pic.twitter.com/kvn1W0ZODD"
        }
      ]
    }
  }
}