{
  "tweet": {
    "edit_info": {
      "initial": {
        "editTweetIds": [
          "821381355326099456"
        ],
        "editableUntil": "2017-01-17T16:39:10.294Z",
        "editsRemaining": "5",
        "isEditEligible": true
      }
    },
    "retweeted": false,
    "source": "<a href=\"http://twitter.com\" rel=\"nofollow\">Twitter Web Client</a>",
    "entities": {
      "hashtags": [],
      "symbols": [],
      "user_mentions": [],
      "urls": []
    },
    "display_text_range": [
      "0",
      "138"
    ],
    "favorite_count": "5",
    "id_str": "821381355326099456",
    "truncated": false,
    "retweet_count": "0",
    "id": "821381355326099456",
    "created_at": "Tue Jan 17 15:39:10 +0000 2017",
    "favorited": false,
    "full_text": "when i tire and a drink a caffeinated drink i feel great empathy for the old man lying on route 2 in viridian city. he just wanted coffee.",
    "lang": "en"
  }
}