{
  "tweet": {
    "edit_info": {
      "initial": {
        "editTweetIds": [
          "1762302761788711204"
        ],
        "editableUntil": "2024-02-27T03:24:55.069Z",
        "editsRemaining": "5",
        "isEditEligible": false
      }
    },
    "retweeted": false,
    "source": "<a href=\"http://twitter.com/download/iphone\" rel=\"nofollow\">Twitter for iPhone</a>",
    "entities": {
      "user_mentions": [
        {
          "name": "Emma",
          "screen_name": "CampbellxEmma",
          "indices": [
            "3",
            "17"
          ],
          "id_str": "616664103",
          "id": "616664103"
        }
      ],
      "urls": [],
      "symbols": [],
      "media": [
        {
          "expanded_url": "https://twitter.com/CampbellxEmma/status/1762207725897822539/photo/1",
          "source_status_id": "1762207725897822539",
          "indices": [
            "21",
            "44"
          ],
          "url": "https://t.co/7PgWZaySZ5",
          "media_url": "http://pbs.twimg.com/media/GHSeWksWEAAMNgq.jpg",
          "id_str": "1762207464852688896",
          "source_user_id": "616664103",
          "id": "1762207464852688896",
          "media_url_https": "https://pbs.twimg.com/media/GHSeWksWEAAMNgq.jpg",
          "source_user_id_str": "616664103",
          "sizes": {
            "medium": {
              "w": "831",
              "h": "1200",
              "resize": "fit"
            },
            "small": {
              "w": "471",
              "h": "680",
              "resize": "fit"
            },
            "thumb": {
              "w": "150",
              "h": "150",
              "resize": "crop"
            },
            "large": {
              "w": "1080",
              "h": "1560",
              "resize": "fit"
            }
          },
          "type": "photo",
          "source_status_id_str": "1762207725897822539",
          "display_url": "pic.twitter.com/7PgWZaySZ5"
        }
      ],
      "hashtags": []
    },
    "display_text_range": [
      "0",
      "44"
    ],
    "favorite_count": "0",
    "id_str": "1762302761788711204",
    "truncated": false,
    "retweet_count": "0",
    "id": "1762302761788711204",
    "possibly_sensitive": false,
    "created_at": "Tue Feb 27 02:24:55 +0000 2024",
    "favorited": false,
    "full_text": "RT @CampbellxEmma: 🥹 https://t.co/7PgWZaySZ5",
    "lang": "qme",
    "extended_entities": {
      "media": [
        {
          "expanded_url": "https://twitter.com/CampbellxEmma/status/1762207725897822539/photo/1",
          "source_status_id": "1762207725897822539",
          "indices": [
            "21",
            "44"
          ],
          "url": "https://t.co/7PgWZaySZ5",
          "media_url": "http://pbs.twimg.com/media/GHSeWksWEAAMNgq.jpg",
          "id_str": "1762207464852688896",
          "source_user_id": "616664103",
          "id": "1762207464852688896",
          "media_url_https": "https://pbs.twimg.com/media/GHSeWksWEAAMNgq.jpg",
          "source_user_id_str": "616664103",
          "sizes": {
            "medium": {
              "w": "831",
              "h": "1200",
              "resize": "fit"
            },
            "small": {
              "w": "471",
              "h": "680",
              "resize": "fit"
            },
            "thumb": {
              "w": "150",
              "h": "150",
              "resize": "crop"
            },
            "large": {
              "w": "1080",
              "h": "1560",
              "resize": "fit"
            }
          },
          "type": "photo",
          "source_status_id_str": "1762207725897822539",
          "display_url": "pic.twitter.com/7PgWZaySZ5"
        },
        {
          "expanded_url": "https://twitter.com/CampbellxEmma/status/1762207725897822539/photo/1",
          "source_status_id": "1762207725897822539",
          "indices": [
            "21",
            "44"
          ],
          "url": "https://t.co/7PgWZaySZ5",
          "media_url": "http://pbs.twimg.com/media/GHSejmIWwAAvQNI.png",
          "id_str": "1762207688576909312",
          "source_user_id": "616664103",
          "id": "1762207688576909312",
          "media_url_https": "https://pbs.twimg.com/media/GHSejmIWwAAvQNI.png",
          "source_user_id_str": "616664103",
          "sizes": {
            "large": {
              "w": "665",
              "h": "203",
              "resize": "fit"
            },
            "thumb": {
              "w": "150",
              "h": "150",
              "resize": "crop"
            },
            "small": {
              "w": "665",
              "h": "203",
              "resize": "fit"
            },
            "medium": {
              "w": "665",
              "h": "203",
              "resize": "fit"
            }
          },
          "type": "photo",
          "source_status_id_str": "1762207725897822539",
          "display_url": "pic.twitter.com/7PgWZaySZ5"
        }
      ]
    }
  }
}