{
  "tweet": {
    "edit_info": {
      "initial": {
        "editTweetIds": [
          "1435718673520635904"
        ],
        "editableUntil": "2021-09-08T22:36:20.787Z",
        "editsRemaining": "5",
        "isEditEligible": true
      }
    },
    "retweeted": false,
    "source": "<a href=\"https://mobile.twitter.com\" rel=\"nofollow\">Twitter Web App</a>",
    "entities": {
      "hashtags": [],
      "symbols": [],
      "user_mentions": [
        {
          "name": "Jevette",
          "screen_name": "itsJevette",
          "indices": [
            "0",
            "11"
          ],
          "id_str": "1073319234",
          "id": "1073319234"
        }
      ],
      "urls": []
    },
    "display_text_range": [
      "0",
      "122"
    ],
    "favorite_count": "2",
    "in_reply_to_status_id_str": "1435718340341690371",
    "id_str": "1435718673520635904",
    "in_reply_to_user_id": "1073319234",
    "truncated": false,
    "retweet_count": "0",
    "id": "1435718673520635904",
    "in_reply_to_status_id": "1435718340341690371",
    "created_at": "Wed Sep 08 21:36:20 +0000 2021",
    "favorited": false,
    "full_text": "@itsJevette have you decided what vices you're gonna pick up now you're being rightfully recognised as a security rockstar",
    "lang": "en",
    "in_reply_to_screen_name": "itsJevette",
    "in_reply_to_user_id_str": "1073319234"
  }
}